{"Product":[{"PutRequest":{"Item":{"Id":{"S":"41cb81"},"Title":{"S":"Item#41cb81"},"Price":{"N":"16727"},"DepartmentId":{"N":"3"}}}},{"PutRequest":{"Item":{"Id":{"S":"7fef52"},"Title":{"S":"Item#7fef52"},"Price":{"N":"505413"},"DepartmentId":{"N":"4"}}}},{"PutRequest":{"Item":{"Id":{"S":"e55252"},"Title":{"S":"Item#e55252"},"Price":{"N":"435103"},"DepartmentId":{"N":"3"}}}},{"PutRequest":{"Item":{"Id":{"S":"473871"},"Title":{"S":"Item#473871"},"Price":{"N":"74056"},"DepartmentId":{"N":"3"}}}},{"PutRequest":{"Item":{"Id":{"S":"56def1"},"Title":{"S":"Item#56def1"},"Price":{"N":"266442"},"DepartmentId":{"N":"3"}}}},{"PutRequest":{"Item":{"Id":{"S":"24284c"},"Title":{"S":"Item#24284c"},"Price":{"N":"593142"},"DepartmentId":{"N":"3"}}}},{"PutRequest":{"Item":{"Id":{"S":"3fcb7f"},"Title":{"S":"Item#3fcb7f"},"Price":{"N":"135825"},"DepartmentId":{"N":"3"}}}},{"PutRequest":{"Item":{"Id":{"S":"57e470"},"Title":{"S":"Item#57e470"},"Price":{"N":"182391"},"DepartmentId":{"N":"5"}}}},{"PutRequest":{"Item":{"Id":{"S":"23346c"},"Title":{"S":"Item#23346c"},"Price":{"N":"509462"},"DepartmentId":{"N":"1"}}}},{"PutRequest":{"Item":{"Id":{"S":"d69a6a"},"Title":{"S":"Item#d69a6a"},"Price":{"N":"152810"},"DepartmentId":{"N":"5"}}}},{"PutRequest":{"Item":{"Id":{"S":"c026c1"},"Title":{"S":"Item#c026c1"},"Price":{"N":"232159"},"DepartmentId":{"N":"4"}}}},{"PutRequest":{"Item":{"Id":{"S":"e43c77"},"Title":{"S":"Item#e43c77"},"Price":{"N":"69328"},"DepartmentId":{"N":"5"}}}},{"PutRequest":{"Item":{"Id":{"S":"3f7eac"},"Title":{"S":"Item#3f7eac"},"Price":{"N":"128859"},"DepartmentId":{"N":"5"}}}},{"PutRequest":{"Item":{"Id":{"S":"f78b6a"},"Title":{"S":"Item#f78b6a"},"Price":{"N":"529503"},"DepartmentId":{"N":"2"}}}},{"PutRequest":{"Item":{"Id":{"S":"d5d583"},"Title":{"S":"Item#d5d583"},"Price":{"N":"269413"},"DepartmentId":{"N":"2"}}}},{"PutRequest":{"Item":{"Id":{"S":"de76bf"},"Title":{"S":"Item#de76bf"},"Price":{"N":"450158"},"DepartmentId":{"N":"2"}}}},{"PutRequest":{"Item":{"Id":{"S":"665b26"},"Title":{"S":"Item#665b26"},"Price":{"N":"67785"},"DepartmentId":{"N":"4"}}}},{"PutRequest":{"Item":{"Id":{"S":"6fa16e"},"Title":{"S":"Item#6fa16e"},"Price":{"N":"208582"},"DepartmentId":{"N":"4"}}}},{"PutRequest":{"Item":{"Id":{"S":"82f2d4"},"Title":{"S":"Item#82f2d4"},"Price":{"N":"22249"},"DepartmentId":{"N":"1"}}}},{"PutRequest":{"Item":{"Id":{"S":"e10f3f"},"Title":{"S":"Item#e10f3f"},"Price":{"N":"288128"},"DepartmentId":{"N":"2"}}}},{"PutRequest":{"Item":{"Id":{"S":"5be86e"},"Title":{"S":"Item#5be86e"},"Price":{"N":"402101"},"DepartmentId":{"N":"4"}}}},{"PutRequest":{"Item":{"Id":{"S":"8c71ca"},"Title":{"S":"Item#8c71ca"},"Price":{"N":"194849"},"DepartmentId":{"N":"1"}}}},{"PutRequest":{"Item":{"Id":{"S":"dfed2a"},"Title":{"S":"Item#dfed2a"},"Price":{"N":"329543"},"DepartmentId":{"N":"5"}}}},{"PutRequest":{"Item":{"Id":{"S":"cf1cfc"},"Title":{"S":"Item#cf1cfc"},"Price":{"N":"175776"},"DepartmentId":{"N":"1"}}}},{"PutRequest":{"Item":{"Id":{"S":"76957b"},"Title":{"S":"Item#76957b"},"Price":{"N":"422691"},"DepartmentId":{"N":"5"}}}}]}