{"SupplierProduct":[{"PutRequest":{"Item":{"ProductId":{"S":"ca538b"},"SupplierId":{"S":"b99027"},"Price":{"S":"389236"},"Quantity":{"N":"560504"}}}},{"PutRequest":{"Item":{"ProductId":{"S":"43ec62"},"SupplierId":{"S":"b99027"},"Price":{"S":"461803"},"Quantity":{"N":"146280"}}}},{"PutRequest":{"Item":{"ProductId":{"S":"2a0c9e"},"SupplierId":{"S":"b99027"},"Price":{"S":"389001"},"Quantity":{"N":"173027"}}}},{"PutRequest":{"Item":{"ProductId":{"S":"c893c8"},"SupplierId":{"S":"b99027"},"Price":{"S":"407674"},"Quantity":{"N":"89652"}}}},{"PutRequest":{"Item":{"ProductId":{"S":"7fef52"},"SupplierId":{"S":"b99027"},"Price":{"S":"509957"},"Quantity":{"N":"252721"}}}},{"PutRequest":{"Item":{"ProductId":{"S":"452454"},"SupplierId":{"S":"b99027"},"Price":{"S":"321657"},"Quantity":{"N":"226206"}}}},{"PutRequest":{"Item":{"ProductId":{"S":"788e95"},"SupplierId":{"S":"b99027"},"Price":{"S":"384691"},"Quantity":{"N":"267512"}}}},{"PutRequest":{"Item":{"ProductId":{"S":"7993df"},"SupplierId":{"S":"b99027"},"Price":{"S":"16160"},"Quantity":{"N":"13436"}}}},{"PutRequest":{"Item":{"ProductId":{"S":"c7295f"},"SupplierId":{"S":"b99027"},"Price":{"S":"96774"},"Quantity":{"N":"355389"}}}},{"PutRequest":{"Item":{"ProductId":{"S":"2b4ab5"},"SupplierId":{"S":"b99027"},"Price":{"S":"216575"},"Quantity":{"N":"577384"}}}},{"PutRequest":{"Item":{"ProductId":{"S":"b307ac"},"SupplierId":{"S":"b99027"},"Price":{"S":"528932"},"Quantity":{"N":"210990"}}}},{"PutRequest":{"Item":{"ProductId":{"S":"ae6e3b"},"SupplierId":{"S":"b99027"},"Price":{"S":"224225"},"Quantity":{"N":"419036"}}}},{"PutRequest":{"Item":{"ProductId":{"S":"123908"},"SupplierId":{"S":"b99027"},"Price":{"S":"451159"},"Quantity":{"N":"47286"}}}},{"PutRequest":{"Item":{"ProductId":{"S":"e14294"},"SupplierId":{"S":"b99027"},"Price":{"S":"38175"},"Quantity":{"N":"267225"}}}},{"PutRequest":{"Item":{"ProductId":{"S":"36510a"},"SupplierId":{"S":"b99027"},"Price":{"S":"380700"},"Quantity":{"N":"114154"}}}},{"PutRequest":{"Item":{"ProductId":{"S":"daa2a5"},"SupplierId":{"S":"b99027"},"Price":{"S":"522373"},"Quantity":{"N":"570230"}}}},{"PutRequest":{"Item":{"ProductId":{"S":"49211f"},"SupplierId":{"S":"b99027"},"Price":{"S":"533475"},"Quantity":{"N":"580511"}}}},{"PutRequest":{"Item":{"ProductId":{"S":"8684da"},"SupplierId":{"S":"b99027"},"Price":{"S":"440400"},"Quantity":{"N":"59285"}}}},{"PutRequest":{"Item":{"ProductId":{"S":"29f67e"},"SupplierId":{"S":"b99027"},"Price":{"S":"347919"},"Quantity":{"N":"338608"}}}},{"PutRequest":{"Item":{"ProductId":{"S":"e31fbb"},"SupplierId":{"S":"b99027"},"Price":{"S":"540682"},"Quantity":{"N":"421002"}}}},{"PutRequest":{"Item":{"ProductId":{"S":"64213d"},"SupplierId":{"S":"b99027"},"Price":{"S":"363461"},"Quantity":{"N":"113391"}}}},{"PutRequest":{"Item":{"ProductId":{"S":"3a91cc"},"SupplierId":{"S":"b99027"},"Price":{"S":"348045"},"Quantity":{"N":"30300"}}}},{"PutRequest":{"Item":{"ProductId":{"S":"caf36e"},"SupplierId":{"S":"b99027"},"Price":{"S":"184410"},"Quantity":{"N":"460582"}}}},{"PutRequest":{"Item":{"ProductId":{"S":"482b54"},"SupplierId":{"S":"b99027"},"Price":{"S":"556508"},"Quantity":{"N":"69334"}}}},{"PutRequest":{"Item":{"ProductId":{"S":"a10927"},"SupplierId":{"S":"b99027"},"Price":{"S":"52792"},"Quantity":{"N":"304337"}}}}]}