{"SupplierProduct":[{"PutRequest":{"Item":{"ProductId":{"S":"916e2d"},"SupplierId":{"S":"7d049a"},"Price":{"S":"378584"},"Quantity":{"N":"6780"}}}},{"PutRequest":{"Item":{"ProductId":{"S":"37c1bf"},"SupplierId":{"S":"7d049a"},"Price":{"S":"24198"},"Quantity":{"N":"406580"}}}},{"PutRequest":{"Item":{"ProductId":{"S":"edb5b4"},"SupplierId":{"S":"7d049a"},"Price":{"S":"229829"},"Quantity":{"N":"36558"}}}},{"PutRequest":{"Item":{"ProductId":{"S":"90f1d6"},"SupplierId":{"S":"7d049a"},"Price":{"S":"64550"},"Quantity":{"N":"180527"}}}},{"PutRequest":{"Item":{"ProductId":{"S":"c1b823"},"SupplierId":{"S":"7d049a"},"Price":{"S":"346720"},"Quantity":{"N":"553402"}}}},{"PutRequest":{"Item":{"ProductId":{"S":"1a0c90"},"SupplierId":{"S":"7d049a"},"Price":{"S":"165443"},"Quantity":{"N":"75077"}}}},{"PutRequest":{"Item":{"ProductId":{"S":"172082"},"SupplierId":{"S":"7d049a"},"Price":{"S":"34561"},"Quantity":{"N":"323856"}}}},{"PutRequest":{"Item":{"ProductId":{"S":"4e7de9"},"SupplierId":{"S":"7d049a"},"Price":{"S":"124435"},"Quantity":{"N":"256620"}}}},{"PutRequest":{"Item":{"ProductId":{"S":"3b01b5"},"SupplierId":{"S":"7d049a"},"Price":{"S":"540527"},"Quantity":{"N":"228000"}}}},{"PutRequest":{"Item":{"ProductId":{"S":"c53991"},"SupplierId":{"S":"7d049a"},"Price":{"S":"489093"},"Quantity":{"N":"183350"}}}},{"PutRequest":{"Item":{"ProductId":{"S":"971adf"},"SupplierId":{"S":"7d049a"},"Price":{"S":"241439"},"Quantity":{"N":"282873"}}}},{"PutRequest":{"Item":{"ProductId":{"S":"e0913d"},"SupplierId":{"S":"7d049a"},"Price":{"S":"446379"},"Quantity":{"N":"14559"}}}},{"PutRequest":{"Item":{"ProductId":{"S":"0c39d2"},"SupplierId":{"S":"7d049a"},"Price":{"S":"364682"},"Quantity":{"N":"24631"}}}},{"PutRequest":{"Item":{"ProductId":{"S":"b50cc3"},"SupplierId":{"S":"7d049a"},"Price":{"S":"112977"},"Quantity":{"N":"194388"}}}},{"PutRequest":{"Item":{"ProductId":{"S":"c7295f"},"SupplierId":{"S":"7d049a"},"Price":{"S":"99784"},"Quantity":{"N":"4052"}}}},{"PutRequest":{"Item":{"ProductId":{"S":"eed113"},"SupplierId":{"S":"7d049a"},"Price":{"S":"604649"},"Quantity":{"N":"167329"}}}},{"PutRequest":{"Item":{"ProductId":{"S":"e10f3f"},"SupplierId":{"S":"7d049a"},"Price":{"S":"289529"},"Quantity":{"N":"142253"}}}},{"PutRequest":{"Item":{"ProductId":{"S":"8efb28"},"SupplierId":{"S":"7d049a"},"Price":{"S":"88155"},"Quantity":{"N":"555939"}}}},{"PutRequest":{"Item":{"ProductId":{"S":"f3c76c"},"SupplierId":{"S":"7d049a"},"Price":{"S":"280341"},"Quantity":{"N":"496632"}}}},{"PutRequest":{"Item":{"ProductId":{"S":"523f05"},"SupplierId":{"S":"7d049a"},"Price":{"S":"278709"},"Quantity":{"N":"591800"}}}},{"PutRequest":{"Item":{"ProductId":{"S":"3f3905"},"SupplierId":{"S":"7d049a"},"Price":{"S":"38647"},"Quantity":{"N":"73425"}}}},{"PutRequest":{"Item":{"ProductId":{"S":"63caaf"},"SupplierId":{"S":"7d049a"},"Price":{"S":"370935"},"Quantity":{"N":"230384"}}}},{"PutRequest":{"Item":{"ProductId":{"S":"40e032"},"SupplierId":{"S":"7d049a"},"Price":{"S":"376643"},"Quantity":{"N":"33158"}}}},{"PutRequest":{"Item":{"ProductId":{"S":"24ccc1"},"SupplierId":{"S":"7d049a"},"Price":{"S":"261465"},"Quantity":{"N":"575188"}}}},{"PutRequest":{"Item":{"ProductId":{"S":"04e33a"},"SupplierId":{"S":"7d049a"},"Price":{"S":"5136"},"Quantity":{"N":"297985"}}}}]}