{"SupplierProduct":[{"PutRequest":{"Item":{"ProductId":{"S":"b4f054"},"SupplierId":{"S":"d257d2"},"Price":{"S":"110034"},"Quantity":{"N":"286321"}}}},{"PutRequest":{"Item":{"ProductId":{"S":"40e032"},"SupplierId":{"S":"d257d2"},"Price":{"S":"377164"},"Quantity":{"N":"478819"}}}},{"PutRequest":{"Item":{"ProductId":{"S":"3c2c7a"},"SupplierId":{"S":"d257d2"},"Price":{"S":"348524"},"Quantity":{"N":"393541"}}}},{"PutRequest":{"Item":{"ProductId":{"S":"788e95"},"SupplierId":{"S":"d257d2"},"Price":{"S":"384012"},"Quantity":{"N":"360256"}}}},{"PutRequest":{"Item":{"ProductId":{"S":"34d00f"},"SupplierId":{"S":"d257d2"},"Price":{"S":"115027"},"Quantity":{"N":"571736"}}}},{"PutRequest":{"Item":{"ProductId":{"S":"7c2dbc"},"SupplierId":{"S":"d257d2"},"Price":{"S":"281016"},"Quantity":{"N":"17352"}}}},{"PutRequest":{"Item":{"ProductId":{"S":"56b937"},"SupplierId":{"S":"d257d2"},"Price":{"S":"144184"},"Quantity":{"N":"497510"}}}},{"PutRequest":{"Item":{"ProductId":{"S":"cf1cfc"},"SupplierId":{"S":"d257d2"},"Price":{"S":"177848"},"Quantity":{"N":"475663"}}}},{"PutRequest":{"Item":{"ProductId":{"S":"971adf"},"SupplierId":{"S":"d257d2"},"Price":{"S":"242504"},"Quantity":{"N":"253365"}}}},{"PutRequest":{"Item":{"ProductId":{"S":"166a7d"},"SupplierId":{"S":"d257d2"},"Price":{"S":"67120"},"Quantity":{"N":"363644"}}}},{"PutRequest":{"Item":{"ProductId":{"S":"f5ee24"},"SupplierId":{"S":"d257d2"},"Price":{"S":"361382"},"Quantity":{"N":"323020"}}}},{"PutRequest":{"Item":{"ProductId":{"S":"cdfa3b"},"SupplierId":{"S":"d257d2"},"Price":{"S":"372264"},"Quantity":{"N":"504639"}}}},{"PutRequest":{"Item":{"ProductId":{"S":"1d799b"},"SupplierId":{"S":"d257d2"},"Price":{"S":"188043"},"Quantity":{"N":"67019"}}}},{"PutRequest":{"Item":{"ProductId":{"S":"715e7e"},"SupplierId":{"S":"d257d2"},"Price":{"S":"237538"},"Quantity":{"N":"288058"}}}},{"PutRequest":{"Item":{"ProductId":{"S":"5be86e"},"SupplierId":{"S":"d257d2"},"Price":{"S":"404145"},"Quantity":{"N":"319334"}}}},{"PutRequest":{"Item":{"ProductId":{"S":"452454"},"SupplierId":{"S":"d257d2"},"Price":{"S":"320065"},"Quantity":{"N":"289292"}}}},{"PutRequest":{"Item":{"ProductId":{"S":"75552e"},"SupplierId":{"S":"d257d2"},"Price":{"S":"189624"},"Quantity":{"N":"182824"}}}},{"PutRequest":{"Item":{"ProductId":{"S":"d3718b"},"SupplierId":{"S":"d257d2"},"Price":{"S":"392840"},"Quantity":{"N":"191628"}}}},{"PutRequest":{"Item":{"ProductId":{"S":"5f1711"},"SupplierId":{"S":"d257d2"},"Price":{"S":"175308"},"Quantity":{"N":"543697"}}}},{"PutRequest":{"Item":{"ProductId":{"S":"9f1f55"},"SupplierId":{"S":"d257d2"},"Price":{"S":"439489"},"Quantity":{"N":"472554"}}}},{"PutRequest":{"Item":{"ProductId":{"S":"c00bf8"},"SupplierId":{"S":"d257d2"},"Price":{"S":"157819"},"Quantity":{"N":"396455"}}}},{"PutRequest":{"Item":{"ProductId":{"S":"123719"},"SupplierId":{"S":"d257d2"},"Price":{"S":"238115"},"Quantity":{"N":"52519"}}}},{"PutRequest":{"Item":{"ProductId":{"S":"4ad81a"},"SupplierId":{"S":"d257d2"},"Price":{"S":"298303"},"Quantity":{"N":"417443"}}}},{"PutRequest":{"Item":{"ProductId":{"S":"9f6f08"},"SupplierId":{"S":"d257d2"},"Price":{"S":"343620"},"Quantity":{"N":"187874"}}}},{"PutRequest":{"Item":{"ProductId":{"S":"810021"},"SupplierId":{"S":"d257d2"},"Price":{"S":"330561"},"Quantity":{"N":"391497"}}}}]}