{"SupplierProduct":[{"PutRequest":{"Item":{"ProductId":{"S":"482b54"},"SupplierId":{"S":"9fc0c9"},"Price":{"S":"556374"},"Quantity":{"N":"106971"}}}},{"PutRequest":{"Item":{"ProductId":{"S":"1d799b"},"SupplierId":{"S":"9fc0c9"},"Price":{"S":"188304"},"Quantity":{"N":"124485"}}}},{"PutRequest":{"Item":{"ProductId":{"S":"c3b18d"},"SupplierId":{"S":"9fc0c9"},"Price":{"S":"567493"},"Quantity":{"N":"73145"}}}},{"PutRequest":{"Item":{"ProductId":{"S":"711b7a"},"SupplierId":{"S":"9fc0c9"},"Price":{"S":"428343"},"Quantity":{"N":"443998"}}}},{"PutRequest":{"Item":{"ProductId":{"S":"56b937"},"SupplierId":{"S":"9fc0c9"},"Price":{"S":"143858"},"Quantity":{"N":"528323"}}}},{"PutRequest":{"Item":{"ProductId":{"S":"d3f473"},"SupplierId":{"S":"9fc0c9"},"Price":{"S":"381326"},"Quantity":{"N":"227984"}}}},{"PutRequest":{"Item":{"ProductId":{"S":"4ad81a"},"SupplierId":{"S":"9fc0c9"},"Price":{"S":"298792"},"Quantity":{"N":"248571"}}}},{"PutRequest":{"Item":{"ProductId":{"S":"20ec59"},"SupplierId":{"S":"9fc0c9"},"Price":{"S":"304727"},"Quantity":{"N":"121481"}}}},{"PutRequest":{"Item":{"ProductId":{"S":"eb8d6b"},"SupplierId":{"S":"9fc0c9"},"Price":{"S":"454472"},"Quantity":{"N":"338770"}}}},{"PutRequest":{"Item":{"ProductId":{"S":"1a48f3"},"SupplierId":{"S":"9fc0c9"},"Price":{"S":"35072"},"Quantity":{"N":"386020"}}}},{"PutRequest":{"Item":{"ProductId":{"S":"cdfa3b"},"SupplierId":{"S":"9fc0c9"},"Price":{"S":"368320"},"Quantity":{"N":"176652"}}}},{"PutRequest":{"Item":{"ProductId":{"S":"9d7622"},"SupplierId":{"S":"9fc0c9"},"Price":{"S":"236362"},"Quantity":{"N":"437460"}}}},{"PutRequest":{"Item":{"ProductId":{"S":"07ef36"},"SupplierId":{"S":"9fc0c9"},"Price":{"S":"172825"},"Quantity":{"N":"413665"}}}},{"PutRequest":{"Item":{"ProductId":{"S":"e0546b"},"SupplierId":{"S":"9fc0c9"},"Price":{"S":"540028"},"Quantity":{"N":"364094"}}}},{"PutRequest":{"Item":{"ProductId":{"S":"58d2d2"},"SupplierId":{"S":"9fc0c9"},"Price":{"S":"269089"},"Quantity":{"N":"503997"}}}},{"PutRequest":{"Item":{"ProductId":{"S":"d69a6a"},"SupplierId":{"S":"9fc0c9"},"Price":{"S":"155107"},"Quantity":{"N":"525628"}}}},{"PutRequest":{"Item":{"ProductId":{"S":"d5d583"},"SupplierId":{"S":"9fc0c9"},"Price":{"S":"270172"},"Quantity":{"N":"570023"}}}},{"PutRequest":{"Item":{"ProductId":{"S":"ca538b"},"SupplierId":{"S":"9fc0c9"},"Price":{"S":"390727"},"Quantity":{"N":"365600"}}}},{"PutRequest":{"Item":{"ProductId":{"S":"982d46"},"SupplierId":{"S":"9fc0c9"},"Price":{"S":"255253"},"Quantity":{"N":"280224"}}}},{"PutRequest":{"Item":{"ProductId":{"S":"e3d39b"},"SupplierId":{"S":"9fc0c9"},"Price":{"S":"182333"},"Quantity":{"N":"468096"}}}},{"PutRequest":{"Item":{"ProductId":{"S":"23346c"},"SupplierId":{"S":"9fc0c9"},"Price":{"S":"510689"},"Quantity":{"N":"523070"}}}},{"PutRequest":{"Item":{"ProductId":{"S":"63caaf"},"SupplierId":{"S":"9fc0c9"},"Price":{"S":"371474"},"Quantity":{"N":"537072"}}}},{"PutRequest":{"Item":{"ProductId":{"S":"ab2cd3"},"SupplierId":{"S":"9fc0c9"},"Price":{"S":"311702"},"Quantity":{"N":"167409"}}}},{"PutRequest":{"Item":{"ProductId":{"S":"4c40c0"},"SupplierId":{"S":"9fc0c9"},"Price":{"S":"40648"},"Quantity":{"N":"431345"}}}},{"PutRequest":{"Item":{"ProductId":{"S":"cf9c80"},"SupplierId":{"S":"9fc0c9"},"Price":{"S":"313425"},"Quantity":{"N":"255354"}}}}]}